async_selective_queue.py
async_selective_queue-0.1.1.post0.dist-info/METADATA
async_selective_queue-0.1.1.post0.dist-info/WHEEL
async_selective_queue-0.1.1.post0.dist-info/licenses/LICENSE
async_selective_queue-0.1.1.post0.dist-info/RECORD
