Metadata-Version: 2.4
Name: async-selective-queue
Version: 0.1.1.post0
Summary: Async queue with selective retrieval
Project-URL: homepage, https://github.com/dbluhm/async-selective-queue
Author-email: Daniel Bluhm <dbluhm@pm.me>
License: Apache-2.0
License-File: LICENSE
Keywords: async,conditional,queue
Requires-Python: <4.0,>=3.9
